dc3client/__init__.py
dc3client/dc3client.py
dc3client/models.py
dc3client-0.0.9.dist-info/LICENSE
dc3client-0.0.9.dist-info/METADATA
dc3client-0.0.9.dist-info/WHEEL
dc3client-0.0.9.dist-info/top_level.txt
dc3client-0.0.9.dist-info/RECORD
