Metadata-Version: 2.1
Name: dc3client
Version: 0.0.9
Summary: dc3client: Client of Digital Curing3.
Home-page: https://github.com/kawamlab/DC3-python
Download-URL: https://github.com/kawamlab/DC3-python
Author: Ryosuke1218
Author-email: 34680324+being24@users.noreply.github.com
Maintainer: Ryosuke1218
Maintainer-email: 34680324+being24@users.noreply.github.com
License: MIT
Keywords: digital-curing3 dc3client
Classifier: License :: OSI Approved :: MIT License
Classifier: Programming Language :: Python :: 3.10
License-File: LICENSE
Requires-Dist: numpy <2.0.0,>=1.25.1
